odoo8_addon_l10n_it_corrispettivi-8.0.1.0.1-nspkg.pth
odoo_addons/l10n_it_corrispettivi/AUTHORS.txt
odoo_addons/l10n_it_corrispettivi/README.rst
odoo_addons/l10n_it_corrispettivi/__init__.py
odoo_addons/l10n_it_corrispettivi/__openerp__.py
odoo_addons/l10n_it_corrispettivi/account.py
odoo_addons/l10n_it_corrispettivi/account_view.xml
odoo_addons/l10n_it_corrispettivi/installer.py
odoo_addons/l10n_it_corrispettivi/installer_view.xml
odoo_addons/l10n_it_corrispettivi/partner_data.xml
odoo_addons/l10n_it_corrispettivi/i18n/it.po
odoo_addons/l10n_it_corrispettivi/i18n/l10n_it_corrispettivi.pot
odoo_addons/l10n_it_corrispettivi/i18n/sl.po
odoo_addons/l10n_it_corrispettivi/static/description/icon.png
odoo8_addon_l10n_it_corrispettivi-8.0.1.0.1.dist-info/METADATA
odoo8_addon_l10n_it_corrispettivi-8.0.1.0.1.dist-info/WHEEL
odoo8_addon_l10n_it_corrispettivi-8.0.1.0.1.dist-info/namespace_packages.txt
odoo8_addon_l10n_it_corrispettivi-8.0.1.0.1.dist-info/top_level.txt
odoo8_addon_l10n_it_corrispettivi-8.0.1.0.1.dist-info/RECORD
